konecty_cli/__init__.py
konecty_cli/consts.py
konecty_cli/main.py
konecty_cli/aimprove/LLM.py
konecty_cli/aimprove/__init__.py
konecty_cli/aimprove/file.py
konecty_cli/aimprove/types.py
konecty_cli/config/__init__.py
konecty_cli/config/add_to_env.py
konecty_cli/config/create.py
konecty_cli/config/edit.py
konecty_cli/config/list.py
konecty_cli/config/types.py
konecty_cli/project/__init__.py
konecty_cli/project/create.py
konecty_cli/utils/config.py
konecty_cli/utils/console.py
konecty_cli-1.0.2.dist-info/METADATA
konecty_cli-1.0.2.dist-info/WHEEL
konecty_cli-1.0.2.dist-info/entry_points.txt
konecty_cli-1.0.2.dist-info/RECORD
